noodle_logging/__init__.py
noodle_logging/decorators.py
noodle_logging/logger.py
noodle_logging/utils.py
noodle_logging-0.3.dist-info/LICENSE
noodle_logging-0.3.dist-info/METADATA
noodle_logging-0.3.dist-info/WHEEL
noodle_logging-0.3.dist-info/top_level.txt
noodle_logging-0.3.dist-info/RECORD
