Metadata-Version: 2.1
Name: noodle-logging
Version: 0.3
Summary: Logging in JSON the easy way!
Home-page: https://github.com/beingaskar/noodle_logging
Author: Ali Askar
Author-email: aliaskar1024@gmail.com
License: UNKNOWN
Platform: UNKNOWN
Classifier: Programming Language :: Python :: 3
Classifier: License :: OSI Approved :: MIT License
Classifier: Operating System :: OS Independent
Requires-Dist: six (==1.12.0)
Requires-Dist: structlog (==21.1.0)
Requires-Dist: python-json-logger (==2.0.1)
